pyformatters_textranksummarizer/__init__.py
pyformatters_textranksummarizer/textranksummarizer.py
pyformatters_textranksummarizer-0.5.154.dist-info/entry_points.txt
pyformatters_textranksummarizer-0.5.154.dist-info/LICENSE
pyformatters_textranksummarizer-0.5.154.dist-info/WHEEL
pyformatters_textranksummarizer-0.5.154.dist-info/METADATA
pyformatters_textranksummarizer-0.5.154.dist-info/RECORD
